README.md
setup.py
./overload/__init__.py
./overload/decorator/__init__.py
./overload/decorator/decorator.py
./overload/exception/__init__.py
./overload/exception/base.py
./overload/exception/overloader.py
./overload/exception/type.py
./overload/implementation/__init__.py
./overload/implementation/base.py
./overload/implementation/function.py
./overload/overloader/__init__.py
./overload/overloader/base.py
./overload/overloader/function.py
./overload/type/__init__.py
./overload/type/type.py
./overload/utils/__init__.py
./overload/utils/property.py
overloader.egg-info/PKG-INFO
overloader.egg-info/SOURCES.txt
overloader.egg-info/dependency_links.txt
overloader.egg-info/top_level.txt