Metadata-Version: 2.1
Name: overloader
Version: 0.1.0
Summary: Python3 function overload lib, based on pure python and native typing.
Home-page: https://github.com/diarts/overload
Author: diarts
Author-email: diarts@mail.ru
License: MIT
Platform: UNKNOWN
Classifier: License :: OSI Approved :: MIT License
Classifier: Programming Language :: Python :: 3
Classifier: Programming Language :: Python :: 3.7
Classifier: Programming Language :: Python :: 3.8
Classifier: Programming Language :: Python :: 3.9
Requires-Python: >=3.7
